RobotRaconteurCompanion/__init__.py
RobotRaconteurCompanion/InfoParser/__init__.py
RobotRaconteurCompanion/StdRobDef/__init__.py
RobotRaconteurCompanion/StdRobDef/com.robotraconteur.action.robdef
RobotRaconteurCompanion/StdRobDef/com.robotraconteur.actuator.robdef
RobotRaconteurCompanion/StdRobDef/com.robotraconteur.bignum.robdef
RobotRaconteurCompanion/StdRobDef/com.robotraconteur.color.robdef
RobotRaconteurCompanion/StdRobDef/com.robotraconteur.datatype.robdef
RobotRaconteurCompanion/StdRobDef/com.robotraconteur.datetime.clock.robdef
RobotRaconteurCompanion/StdRobDef/com.robotraconteur.datetime.robdef
RobotRaconteurCompanion/StdRobDef/com.robotraconteur.device.clock.robdef
RobotRaconteurCompanion/StdRobDef/com.robotraconteur.device.isoch.robdef
RobotRaconteurCompanion/StdRobDef/com.robotraconteur.device.robdef
RobotRaconteurCompanion/StdRobDef/com.robotraconteur.eventlog.robdef
RobotRaconteurCompanion/StdRobDef/com.robotraconteur.fiducial.robdef
RobotRaconteurCompanion/StdRobDef/com.robotraconteur.geometry.robdef
RobotRaconteurCompanion/StdRobDef/com.robotraconteur.geometry.shapes.robdef
RobotRaconteurCompanion/StdRobDef/com.robotraconteur.geometryf.robdef
RobotRaconteurCompanion/StdRobDef/com.robotraconteur.geometryi.robdef
RobotRaconteurCompanion/StdRobDef/com.robotraconteur.gps.robdef
RobotRaconteurCompanion/StdRobDef/com.robotraconteur.hid.joystick.robdef
RobotRaconteurCompanion/StdRobDef/com.robotraconteur.identifier.robdef
RobotRaconteurCompanion/StdRobDef/com.robotraconteur.image.robdef
RobotRaconteurCompanion/StdRobDef/com.robotraconteur.imaging.camerainfo.robdef
RobotRaconteurCompanion/StdRobDef/com.robotraconteur.imaging.robdef
RobotRaconteurCompanion/StdRobDef/com.robotraconteur.imu.robdef
RobotRaconteurCompanion/StdRobDef/com.robotraconteur.laserscan.robdef
RobotRaconteurCompanion/StdRobDef/com.robotraconteur.laserscanner.robdef
RobotRaconteurCompanion/StdRobDef/com.robotraconteur.lighting.robdef
RobotRaconteurCompanion-0.4.0.dist-info/LICENSE.txt
RobotRaconteurCompanion-0.4.0.dist-info/METADATA
RobotRaconteurCompanion-0.4.0.dist-info/WHEEL
RobotRaconteurCompanion-0.4.0.dist-info/top_level.txt
RobotRaconteurCompanion-0.4.0.dist-info/RECORD
