Metadata-Version: 2.1
Name: RobotRaconteurCompanion
Version: 0.4.0
Summary: Robot Raconteur Python Companion Library
Home-page: https://github.com/robotraconteur/robotraconteur_companion_python
Author: John Wason
Author-email: wason@wasontech.com
License-File: LICENSE.txt
Requires-Dist: RobotRaconteur >=1.1.1
Requires-Dist: numpy
Requires-Dist: PyYAML
Requires-Dist: setuptools
Requires-Dist: importlib-resources
Requires-Dist: general-robotics-toolbox >=0.7.1
Provides-Extra: test
Requires-Dist: pytest ; extra == 'test'
